Workbook
Name Slicer_Category: #N/A

Sheet Business Questions
A1: Business Questions:
A4: 1. How is the business performing overall?
A6: 2. How have revenue and profit changed over time?
A8: 3. Which products are driving sales?
A10: 4. Which products are driving profitability?
A12: 5. Which categories and brands perform best?
A14: 6. Which countries contribute the most to the business?
A16: 7. What purchasing patterns can we identify from payment method and product preferences?
A18: 8. What actions should management take based on the findings?

Sheet Shoe Sales
A1: Date | B1: Product | C1: Category | D1: Color | E1: Brand | F1: Country | G1: Quantity | H1: Payment Type | I1: Unit_price | J1: Unit_cost | K1: Revenue | L1: Total_cost | M1: Profit | N1: Profit-margin
A2: 46161 | B2: Monk Straps | C2: Formal | D2: Red | E2: =PROPER(TRIM(CLEAN(ShoeSales[[#This Row],[Brand]]))) -> Nike | F2: Uganda | G2: 7 | H2: Bank Transfer | I2: =VLOOKUP(ShoeSales[[#This Row],[Product]],Price!$A$2:C9,2,) -> 89 | J2: =VLOOKUP(ShoeSales[[#This Row],[Product]],Price!$A$2:C9,3,) -> 47 | K2: =ShoeSales[[#This Row],[Quantity]]*ShoeSales[[#This Row],[Unit_price]] -> 623 | L2: =ShoeSales[[#This Row],[Quantity]]*ShoeSales[[#This Row],[Unit_cost]] -> 329 | M2: =ShoeSales[[#This Row],[Revenue]]-ShoeSales[[#This Row],[Total_cost]] -> 294 | N2: =ShoeSales[[#This Row],[Profit]]/ShoeSales[[#This Row],[Revenue]] -> 0.47191011
A3: 46199 | B3: Loafers | C3: Formal | D3: Black | E3: =PROPER(TRIM(CLEAN(ShoeSales[[#This Row],[Brand]]))) -> Nike | F3: Uganda | G3: 1 | H3: Card | I3: =VLOOKUP(ShoeSales[[#This Row],[Product]],Price!$A$2:C10,2,) -> 54 | J3: =VLOOKUP(ShoeSales[[#This Row],[Product]],Price!$A$2:C10,3,) -> 28 | K3: =ShoeSales[[#This Row],[Quantity]]*ShoeSales[[#This Row],[Unit_price]] -> 54 | L3: =ShoeSales[[#This Row],[Quantity]]*ShoeSales[[#This Row],[Unit_cost]] -> 28 | M3: =ShoeSales[[#This Row],[Revenue]]-ShoeSales[[#This Row],[Total_cost]] -> 26 | N3: =ShoeSales[[#This Row],[Profit]]/ShoeSales[[#This Row],[Revenue]] -> 0.48148148
A4: 46172 | B4: Derby | C4: Formal | D4: Green | E4: =PROPER(TRIM(CLEAN(ShoeSales[[#This Row],[Brand]]))) -> Clarks | F4: Nigeria | G4: 7 | H4: Bank Transfer | I4: =VLOOKUP(ShoeSales[[#This Row],[Product]],Price!$A$2:C11,2,) -> 32 | J4: =VLOOKUP(ShoeSales[[#This Row],[Product]],Price!$A$2:C11,3,) -> 14 | K4: =ShoeSales[[#This Row],[Quantity]]*ShoeSales[[#This Row],[Unit_price]] -> 224 | L4: =ShoeSales[[#This Row],[Quantity]]*ShoeSales[[#This Row],[Unit_cost]] -> 98 | M4: =ShoeSales[[#This Row],[Revenue]]-ShoeSales[[#This Row],[Total_cost]] -> 126 | N4: =ShoeSales[[#This Row],[Profit]]/ShoeSales[[#This Row],[Revenue]] -> 0.5625
A5: 46214 | B5: Boots | C5: Utility | D5: Black | E5: =PROPER(TRIM(CLEAN(ShoeSales[[#This Row],[Brand]]))) -> Nike | F5: Canada | G5: 6 | H5: Bank Transfer | I5: =VLOOKUP(ShoeSales[[#This Row],[Product]],Price!$A$2:C12,2,) -> 76 | J5: =VLOOKUP(ShoeSales[[#This Row],[Product]],Price!$A$2:C12,3,) -> 39 | K5: =ShoeSales[[#This Row],[Quantity]]*ShoeSales[[#This Row],[Unit_price]] -> 456 | L5: =ShoeSales[[#This Row],[Quantity]]*ShoeSales[[#This Row],[Unit_cost]] -> 234 | M5: =ShoeSales[[#This Row],[Revenue]]-ShoeSales[[#This Row],[Total_cost]] -> 222 | N5: =ShoeSales[[#This Row],[Profit]]/ShoeSales[[#This Row],[Revenue]] -> 0.48684211
A6: 46130 | B6: Boots | C6: Casual | D6: Red | E6: =PROPER(TRIM(CLEAN(ShoeSales[[#This Row],[Brand]]))) -> Clarks | F6: UK | G6: 6 | H6: Bank Transfer | I6: =VLOOKUP(ShoeSales[[#This Row],[Product]],Price!$A$2:C13,2,) -> 76 | J6: =VLOOKUP(ShoeSales[[#This Row],[Product]],Price!$A$2:C13,3,) -> 39 | K6: =ShoeSales[[#This Row],[Quantity]]*ShoeSales[[#This Row],[Unit_price]] -> 456 | L6: =ShoeSales[[#This Row],[Quantity]]*ShoeSales[[#This Row],[Unit_cost]] -> 234 | M6: =ShoeSales[[#This Row],[Revenue]]-ShoeSales[[#This Row],[Total_cost]] -> 222 | N6: =ShoeSales[[#This Row],[Profit]]/ShoeSales[[#This Row],[Revenue]] -> 0.48684211
A7: 46093 | B7: Canvas | C7: Utility | D7: Blue | E7: =PROPER(TRIM(CLEAN(ShoeSales[[#This Row],[Brand]]))) -> Nike | F7: Ghana | G7: 6 | H7: Card | I7: =VLOOKUP(ShoeSales[[#This Row],[Product]],Price!$A$2:C14,2,) -> 128 | J7: =VLOOKUP(ShoeSales[[#This Row],[Product]],Price!$A$2:C14,3,) -> 72 | K7: =ShoeSales[[#This Row],[Quantity]]*ShoeSales[[#This Row],[Unit_price]] -> 768 | L7: =ShoeSales[[#This Row],[Quantity]]*ShoeSales[[#This Row],[Unit_cost]] -> 432 | M7: =ShoeSales[[#This Row],[Revenue]]-ShoeSales[[#This Row],[Total_cost]] -> 336 | N7: =ShoeSales[[#This Row],[Profit]]/ShoeSales[[#This Row],[Revenue]] -> 0.4375
A8: 46191 | B8: Canvas | C8: Formal | D8: Green | E8: =PROPER(TRIM(CLEAN(ShoeSales[[#This Row],[Brand]]))) -> Clarks | F8: USA | G8: 13 | H8: Cash | I8: =VLOOKUP(ShoeSales[[#This Row],[Product]],Price!$A$2:C15,2,) -> 128 | J8: =VLOOKUP(ShoeSales[[#This Row],[Product]],Price!$A$2:C15,3,) -> 72 | K8: =ShoeSales[[#This Row],[Quantity]]*ShoeSales[[#This Row],[Unit_price]] -> 1664 | L8: =ShoeSales[[#This Row],[Quantity]]*ShoeSales[[#This Row],[Unit_cost]] -> 936 | M8: =ShoeSales[[#This Row],[Revenue]]-ShoeSales[[#This Row],[Total_cost]] -> 728 | N8: =ShoeSales[[#This Row],[Profit]]/ShoeSales[[#This Row],[Revenue]] -> 0.4375
A9: 46212 | B9: Monk Straps | C9: Formal | D9: Brown | E9: =PROPER(TRIM(CLEAN(ShoeSales[[#This Row],[Brand]]))) -> Timberland | F9: USA | G9: 12 | H9: Cash | I9: =VLOOKUP(ShoeSales[[#This Row],[Product]],Price!$A$2:C16,2,) -> 89 | J9: =VLOOKUP(ShoeSales[[#This Row],[Product]],Price!$A$2:C16,3,) -> 47 | K9: =ShoeSales[[#This Row],[Quantity]]*ShoeSales[[#This Row],[Unit_price]] -> 1068 | L9: =ShoeSales[[#This Row],[Quantity]]*ShoeSales[[#This Row],[Unit_cost]] -> 564 | M9: =ShoeSales[[#This Row],[Revenue]]-ShoeSales[[#This Row],[Total_cost]] -> 504 | N9: =ShoeSales[[#This Row],[Profit]]/ShoeSales[[#This Row],[Revenue]] -> 0.47191011
A10: 46038 | B10: Derby | C10: Formal | D10: Green | E10: =PROPER(TRIM(CLEAN(ShoeSales[[#This Row],[Brand]]))) -> Clarks | F10: Australia | G10: 10 | H10: Cash | I10: =VLOOKUP(ShoeSales[[#This Row],[Product]],Price!$A$2:C17,2,) -> 32 | J10: =VLOOKUP(ShoeSales[[#This Row],[Product]],Price!$A$2:C17,3,) -> 14 | K10: =ShoeSales[[#This Row],[Quantity]]*ShoeSales[[#This Row],[Unit_price]] -> 320 | L10: =ShoeSales[[#This Row],[Quantity]]*ShoeSales[[#This Row],[Unit_cost]] -> 140 | M10: =ShoeSales[[#This Row],[Revenue]]-ShoeSales[[#This Row],[Total_cost]] -> 180 | N10: =ShoeSales[[#This Row],[Profit]]/ShoeSales[[#This Row],[Revenue]] -> 0.5625
A11: 46182 | B11: Oxford | C11: Formal | D11: Black | E11: =PROPER(TRIM(CLEAN(ShoeSales[[#This Row],[Brand]]))) -> Clarks | F11: Cyprus | G11: 15 | H11: Mobile Money | I11: =VLOOKUP(ShoeSales[[#This Row],[Product]],Price!$A$2:C18,2,) -> 105 | J11: =VLOOKUP(ShoeSales[[#This Row],[Product]],Price!$A$2:C18,3,) -> 58 | K11: =ShoeSales[[#This Row],[Quantity]]*ShoeSales[[#This Row],[Unit_price]] -> 1575 | L11: =ShoeSales[[#This Row],[Quantity]]*ShoeSales[[#This Row],[Unit_cost]] -> 870 | M11: =ShoeSales[[#This Row],[Revenue]]-ShoeSales[[#This Row],[Total_cost]] -> 705 | N11: =ShoeSales[[#This Row],[Profit]]/ShoeSales[[#This Row],[Revenue]] -> 0.44761905
A12: 46132 | B12: Boots | C12: Formal | D12: Brown | E12: =PROPER(TRIM(CLEAN(ShoeSales[[#This Row],[Brand]]))) -> Clarks | F12: India | G12: 8 | H12: Bank Transfer | I12: =VLOOKUP(ShoeSales[[#This Row],[Product]],Price!$A$2:C19,2,) -> 76 | J12: =VLOOKUP(ShoeSales[[#This Row],[Product]],Price!$A$2:C19,3,) -> 39 | K12: =ShoeSales[[#This Row],[Quantity]]*ShoeSales[[#This Row],[Unit_price]] -> 608 | L12: =ShoeSales[[#This Row],[Quantity]]*ShoeSales[[#This Row],[Unit_cost]] -> 312 | M12: =ShoeSales[[#This Row],[Revenue]]-ShoeSales[[#This Row],[Total_cost]] -> 296 | N12: =ShoeSales[[#This Row],[Profit]]/ShoeSales[[#This Row],[Revenue]] -> 0.48684211
A13: 46097 | B13: Loafers | C13: Casual | D13: Green | E13: =PROPER(TRIM(CLEAN(ShoeSales[[#This Row],[Brand]]))) -> Clarks | F13: Australia | G13: 9 | H13: Cash | I13: =VLOOKUP(ShoeSales[[#This Row],[Product]],Price!$A$2:C20,2,) -> 54 | J13: =VLOOKUP(ShoeSales[[#This Row],[Product]],Price!$A$2:C20,3,) -> 28 | K13: =ShoeSales[[#This Row],[Quantity]]*ShoeSales[[#This Row],[Unit_price]] -> 486 | L13: =ShoeSales[[#This Row],[Quantity]]*ShoeSales[[#This Row],[Unit_cost]] -> 252 | M13: =ShoeSales[[#This Row],[Revenue]]-ShoeSales[[#This Row],[Total_cost]] -> 234 | N13: =ShoeSales[[#This Row],[Profit]]/ShoeSales[[#This Row],[Revenue]] -> 0.48148148
... A501: 46218 | B501: Derby | C501: Casual | D501: Red | E501: =PROPER(TRIM(CLEAN(ShoeSales[[#This Row],[Brand]]))) -> Clarks | F501: Germany | G501: 4 | H501: Bank Transfer | I501: =VLOOKUP(ShoeSales[[#This Row],[Product]],Price!$A$2:C508,2,) -> 32 | J501: =VLOOKUP(ShoeSales[[#This Row],[Product]],Price!$A$2:C508,3,) -> 14 | K501: =ShoeSales[[#This Row],[Quantity]]*ShoeSales[[#This Row],[Unit_price]] -> 128 | L501: =ShoeSales[[#This Row],[Quantity]]*ShoeSales[[#This Row],[Unit_cost]] -> 56 | M501: =ShoeSales[[#This Row],[Revenue]]-ShoeSales[[#This Row],[Total_cost]] -> 72 | N501: =ShoeSales[[#This Row],[Profit]]/ShoeSales[[#This Row],[Revenue]] -> 0.5625

Sheet Price
A1: Product | B1: Price | C1: Cost
A2: Monk Straps | B2: 89 | C2: 47
A3: Loafers | B3: 54 | C3: 28
A4: Derby | B4: 32 | C4: 14
A5: Boots | B5: 76 | C5: 39
A6: Canvas | B6: 128 | C6: 72
A7: Oxford | B7: 105 | C7: 58
A8: Brogues | B8: 112 | C8: 64
A9: Slippers | B9: 119 | C9: 67

Sheet PivotTables
AD1: Revenue by Category
I2: Revenue by Products | T2: Monthly Revenue | AD2: Category | AE2: Revenue | AM2: Revenue by Brand
B3: Revenue | C3: Total_cost | D3: Profit | E3: Profit Margin | F3: Quantity Sold | I3: Products | J3: Sum of Profit | K3: Sum of Revenue | T3: Months | U3: Sum of Revenue | AD3: Casual | AE3: 82917 | AM3: Brand | AN3: Revenue | AW3: Revenue & Profit by Country | BJ3: Payment type
B4: 355048 | C4: 192713 | D4: 162335 | E4: 0.47075624 | F4: 4012 | I4: Boots | J4: 19980 | K4: 41040 | T4: Jan | U4: 43801 | AD4: Formal | AE4: 179935 | AM4: Clarks | AN4: 123543 | AW4: Country | AX4: Revenue | AY4: Profit | BJ4: Payment type | BK4: Count of Payment Type
I5: Brogues | J5: 25104 | K5: 58576 | T5: Feb | U5: 40664 | AD5: Open | AE5: 53035 | AM5: Nike | AN5: 54029 | AW5: USA | AX5: 39127 | AY5: 17892 | BJ5: Bank Transfer | BK5: 135
I6: Canvas | J6: 27776 | K6: 63488 | T6: Mar | U6: 45492 | AD6: Utility | AE6: 39161 | AM6: Steve Madden | AN6: 43855 | AW6: UK | AX6: 32871 | AY6: 15393 | BJ6: Card | BK6: 137
I7: Derby | J7: 9396 | K7: 16704 | T7: Apr | U7: 44204 | AD7: Grand Total | AE7: 355048 | AM7: Timberland | AN7: 38824 | AW7: Ghana | AX7: 32026 | AY7: 14468 | BJ7: Cash | BK7: 125
I8: Loafers | J8: 11778 | K8: 24462 | T8: May | U8: 44578 | AM8: Zara | AN8: 94797 | AW8: Zimbabwe | AX8: 30124 | AY8: 13584 | BJ8: Mobile Money | BK8: 103
I9: Monk Straps | J9: 24150 | K9: 51175 | T9: Jun | U9: 70771 | AM9: Grand Total | AN9: 355048 | AW9: India | AX9: 29392 | AY9: 13441 | BJ9: Grand Total | BK9: 500
I10: Oxford | J10: 26367 | K10: 58905 | T10: Jul | U10: 49497 | AW10: Cyprus | AX10: 26531 | AY10: 12210
I11: Slippers | J11: 17784 | K11: 40698 | T11: Aug | U11: 16041 | AW11: Kenya | AX11: 26595 | AY11: 11974
I12: Grand Total | J12: 162335 | K12: 355048 | T12: Grand Total | U12: 355048 | AW12: Uganda | AX12: 25851 | AY12: 11798
AW13: Nigeria | AX13: 20798 | AY13: 9638
AW14: Philippines | AX14: 20810 | AY14: 9548
AW15: Germany | AX15: 20204 | AY15: 9010
AW16: Australia | AX16: 18562 | AY16: 8476
AW17: Canada | AX17: 17565 | AY17: 8102
AW18: Albania | AX18: 14592 | AY18: 6801
AW19: Grand Total | AX19: 355048 | AY19: 162335

Sheet Dashboard
